codegen/__init__.py
codegen/__main__.py
codegen/generator.py
codegen/network.py
codegen/query_presets.py
codegen/src/__init__.py
codegen/src/base_class.py
codegen/src/consts.py
codegen/src/enums.py
codegen/src/extractor.py
codegen/src/printer.py
codegen/src/priority.py
codegen/src/sp_builder.py
codegen/src/sp_schema.py
codegen/src/utils.py
codegen/src/templates/__init__.py
codegen/src/templates/circular_class_template
codegen/src/templates/enum_template
codegen/src/templates/mutation_template
codegen/src/templates/query_template
codegen/src/templates/scalar_template
codegen/src/templates/simple_type_template
codegen/src/templates/type_refs_template
codegen/src/templates/type_template
codegen/src/templates/unions_template
graphql_dataclass-1.0.6.data/data/config.ini
pygqlmap/__init__.py
pygqlmap/components.py
pygqlmap/config.ini
pygqlmap/enums.py
pygqlmap/gql_operations.py
pygqlmap/gql_types.py
pygqlmap/helper.py
pygqlmap/network.py
pygqlmap/src/__init__.py
pygqlmap/src/arg_builtin.py
pygqlmap/src/base.py
pygqlmap/src/builder.py
pygqlmap/src/components.py
pygqlmap/src/consts.py
pygqlmap/src/enums.py
pygqlmap/src/gql_init.py
pygqlmap/src/translator.py
pygqlmap/src/utils.py
graphql_dataclass-1.0.6.dist-info/LICENSE
graphql_dataclass-1.0.6.dist-info/METADATA
graphql_dataclass-1.0.6.dist-info/WHEEL
graphql_dataclass-1.0.6.dist-info/entry_points.txt
graphql_dataclass-1.0.6.dist-info/top_level.txt
graphql_dataclass-1.0.6.dist-info/RECORD
