Metadata-Version: 2.1
Name: graphql-dataclass
Version: 1.0.6
Summary: A python library to generate dataclasses for GraphQL types
Home-page: https://github.com/nikikuzi/graphql-dataclass
Author: Mikita Kuzniatsou, Alex Dap
Author-email: Mikita Kuzniatsou <nikikuzi@gmail.com>, Alex Dap <shlisi2017@gmail.com>
License: MIT License
Project-URL: Homepage, https://github.com/nikikuzi/graphql-dataclass/
Project-URL: Source Code, https://github.com/nikikuzi/graphql-dataclass/tree/1.0.6
Project-URL: Bug Tracker, https://github.com/nikikuzi/graphql-dataclass/issues
Project-URL: Release Notes, https://github.com/nikikuzi/graphql-dataclass/tree/1.0.6/RELEASE_NOTES.MD
Keywords: python,graphql,mapping,dataclass
Classifier: Programming Language :: Python :: 3
Classifier: License :: OSI Approved :: MIT License
Classifier: Operating System :: OS Independent
Requires-Python: >=3.10
License-File: LICENSE
Requires-Dist: anyio ==3.1.0
Requires-Dist: autoflake ==2.3.1
Requires-Dist: black ==24.8.0
Requires-Dist: isort ==5.13.2
